opendart/__init__.py
opendart/example.py
opendart/utils.py
opendart/api/__init__.py
opendart/api/business_report.py
opendart/api/common.py
opendart/api/public_notice.py
opendart/async_apis/__init__.py
opendart/async_apis/business_report.py
opendart/async_apis/common.py
opendart/async_apis/public_notice.py
opendart/config/__init__.py
opendart/config/api_urls.py
opendart/config/environments.py
opendart/models/__init__.py
opendart/models/business_report.py
opendart/models/common.py
opendart/models/public_notice.py
opendart/models/business_report/__init__.py
OpenDart-0.1.0.dist-info/LICENSE
OpenDart-0.1.0.dist-info/METADATA
OpenDart-0.1.0.dist-info/WHEEL
OpenDart-0.1.0.dist-info/top_level.txt
OpenDart-0.1.0.dist-info/RECORD
