Metadata-Version: 2.1
Name: OpenDart
Version: 0.1.0
Summary: 전자공시 OPEN DART 시스템 API
Author: jihogrammer
Author-email: jihogrammer@gmail.com
License: MIT
Classifier: Development Status :: 2 - Pre-Alpha
Classifier: Natural Language :: Korean
Classifier: Environment :: Web Environment
Classifier: Programming Language :: Python :: 3.9
Classifier: License :: OSI Approved :: MIT License
Classifier: Topic :: Office/Business
License-File: LICENSE
Requires-Dist: python-dotenv
Requires-Dist: requests
Requires-Dist: aiohttp
Requires-Dist: xmltodict
